LICENSE
README.md
pyproject.toml
metadynminer/__init__.py
metadynminer.egg-info/PKG-INFO
metadynminer.egg-info/SOURCES.txt
metadynminer.egg-info/dependency_links.txt
metadynminer.egg-info/requires.txt
metadynminer.egg-info/top_level.txt
tests/test_fast.py
tests/test_fep.py
tests/test_minima.py
tests/test_orig.py
tests/test_readhills.py