Metadata-Version: 2.4
Name: metadynminer
Version: 0.9.2
Summary: Python package for efficient analysis of HILLS files generated by Plumed metadynamics simulations. 
Author-email: Jan Beránek <Jan1.Beranek@vscht.cz>
License-Expression: GPL-3.0-or-later
Project-URL: Homepage, https://metadynreporter.cz/
Project-URL: Documentation, https://metadynreporter.cz/manual/index.html
Project-URL: Repository, https://github.com/Jan8be/metadynminer.py
Project-URL: Issues, https://github.com/Jan8be/metadynminer.py/issues
Keywords: metadynamics,analysis,visualization,Plumed
Classifier: Development Status :: 4 - Beta
Classifier: Intended Audience :: Science/Research
Classifier: Topic :: Scientific/Engineering :: Bio-Informatics
Classifier: Programming Language :: Python :: 3
Classifier: Programming Language :: Python :: 3.9
Classifier: Programming Language :: Python :: 3.10
Classifier: Programming Language :: Python :: 3.11
Classifier: Programming Language :: Python :: 3.12
Classifier: Programming Language :: Python :: 3.13
Requires-Python: >=3.9
License-File: LICENSE
Requires-Dist: numpy>=1.21.6
Requires-Dist: matplotlib>=3.5.3
Requires-Dist: pandas>=1.3.5
Requires-Dist: pyvista>=0.43.0
Requires-Dist: imageio>=2.31.1
Dynamic: license-file
